assistant/__init__.py
assistant/__version__.py
assistant/cli.py
assistant/welcome.py
assistant/agents/__init__.py
assistant/agents/agent_discovery.py
assistant/agents/agent_repo.py
assistant/agents/query_analyzer.py
assistant/agents/shell.py
assistant/agents/shell_constants.py
assistant/agents/shell_help.py
assistant/agents/integrations/__init__.py
assistant/agents/integrations/github.py
assistant/agents/integrations/jira.py
assistant/agents/tools/__init__.py
assistant/agents/tools/binary_file.py
assistant/agents/tools/project.py
assistant/agents/tools/system_shell.py
assistant/agents/tools/text_file.py
assistant/agents/tools/time.py
assistant/agents/utils/__init__.py
assistant/agents/utils/prompts.py
assistant/agents/web/__init__.py
assistant/agents/web/download.py
assistant/agents/web/google_search.py
assistant/agents/web/screenshot.py
assistant/agents/web/webpage.py
assistant/commands/__init__.py
assistant/config/__init__.py
assistant/config/manager.py
assistant/core/__init__.py
assistant/core/data_types.py
assistant/core/faker.py
assistant/core/templates.py
assistant/integrations/__init__.py
assistant/integrations/openspec.py
assistant/llm/__init__.py
assistant/llm/agent_client.py
assistant/llm/client.py
assistant/llm/history.py
assistant/llm/utils.py
assistant/mcp/__init__.py
assistant/mcp/client.py
assistant/utils/__init__.py
assistant/utils/json.py
assistant/utils/path.py
assistant/utils/source_code.py
assistant/utils/cli/__init__.py
assistant/utils/cli/console.py
assistant/utils/cli/executor.py
assistant/utils/llm/__init__.py
assistant/utils/llm/error_logger.py
assistant/utils/llm/img_utils.py
assistant/utils/llm/token_utils.py
fsc_assistant-0.1.4.dist-info/licenses/LICENSE
fsc_assistant-0.1.4.dist-info/METADATA
fsc_assistant-0.1.4.dist-info/WHEEL
fsc_assistant-0.1.4.dist-info/entry_points.txt
fsc_assistant-0.1.4.dist-info/top_level.txt
fsc_assistant-0.1.4.dist-info/RECORD
