Metadata-Version: 2.4
Name: fsc-assistant
Version: 0.1.4
Summary: Add your description here
Author-email: Sunny Liu <sunnyliu2@gmail.com>
License: MIT
Project-URL: Homepage, https://github.com/devsunny/fsc-assistant
Project-URL: Documentation, https://github.com/devsunny/fsc-assistant/README.md
Project-URL: Repository, https://github.com/devsunny/fsc-assistant
Classifier: Development Status :: 4 - Beta
Classifier: Intended Audience :: Developers
Classifier: License :: OSI Approved :: MIT License
Classifier: Programming Language :: Python :: 3
Classifier: Programming Language :: Python :: 3.12
Classifier: Programming Language :: Python :: 3.13
Classifier: Programming Language :: Python :: 3.14
Classifier: Topic :: Utilities
Requires-Python: >=3.12
License-File: LICENSE
Requires-Dist: click>=8.3.1
Requires-Dist: openai>=2.7.1
Requires-Dist: pillow>=2.8.00
Requires-Dist: prompt-toolkit>=3.0.52
Requires-Dist: rich>=14.2.0
Requires-Dist: tenacity>=9.1.2
Requires-Dist: tomlkit>=0.13.3
Requires-Dist: certifi>=2025.11.12
Requires-Dist: pygithub>=2.8.1
Requires-Dist: jira>=3.10.5
Requires-Dist: fastmcp>=2.13.1
Requires-Dist: httpx>=0.28.1
Requires-Dist: google-api-python-client>=2.100.0
Dynamic: license-file
